comma_agents/__init__.py
comma_agents/agents/__init__.py
comma_agents/agents/base_agent.py
comma_agents/agents/user_agent.py
comma_agents/cli/main.py
comma_agents/code_interpreters/__init__.py
comma_agents/code_interpreters/code_interpreter.py
comma_agents/code_interpreters/code_interpreter_language_handler.py
comma_agents/code_interpreters/languages/__init__.py
comma_agents/code_interpreters/languages/python.py
comma_agents/code_interpreters/languages/sh.py
comma_agents/flows/__init__.py
comma_agents/flows/base_flow.py
comma_agents/flows/broadcast_flow.py
comma_agents/flows/cycle_flow.py
comma_agents/flows/cycle_observer_flow.py
comma_agents/flows/infinite_cycle_flow.py
comma_agents/flows/sequential_flow.py
comma_agents/prompts/__init__.py
comma_agents/prompts/base_prompt.py
comma_agents/strategies/__init__.py
comma_agents/strategies/strategy.py
comma_agents/utils/__init__.py
comma_agents/utils/cache/__init__.py
comma_agents/utils/misc/__init__.py
comma_agents/utils/misc/or_one_value_to_array.py
comma_agents/utils/print_formats/__init__.py
comma_agents/utils/print_formats/flow_print_formats.py
comma_agents-0.0.9.dist-info/LICENSE.md
comma_agents-0.0.9.dist-info/METADATA
comma_agents-0.0.9.dist-info/WHEEL
comma_agents-0.0.9.dist-info/entry_points.txt
comma_agents-0.0.9.dist-info/RECORD
