Metadata-Version: 2.1
Name: comma-agents
Version: 0.0.9
Summary: A way to elevate your AI workflow with Comma Agents, a versatile Python library designed for seamless AI model integration and automation. Perfect for developers looking to enhance efficiency in local or remote environments, it offers customizable AI flows and scalable solutions. Streamline your projects with Comma Agents, the ideal tool for Python-based AI automation.
Home-page: https://commaagents.com/
License: MIT
Author: Nathaniel Hatch-Martinez
Author-email: nhm@cloai.com
Requires-Python: >=3.9,<4.0
Classifier: License :: OSI Approved :: MIT License
Classifier: Programming Language :: Python :: 3
Classifier: Programming Language :: Python :: 3.9
Classifier: Programming Language :: Python :: 3.10
Classifier: Programming Language :: Python :: 3.11
Classifier: Programming Language :: Python :: 3.12
Requires-Dist: click (>=8.1.7,<9.0.0)
Requires-Dist: colorama (>=0.4.6,<0.5.0)
Requires-Dist: gitpython (>=3.1.40,<4.0.0)
Requires-Dist: platformdirs (>=4.2.2,<5.0.0)
Requires-Dist: pydantic (>=2.6.4,<3.0.0)
Requires-Dist: pyyaml (>=6.0.1,<7.0.0)
Requires-Dist: xxhash (>=3.5.0,<4.0.0)
Project-URL: Documentation, https://commaagents.com/docs
Project-URL: Repository, https://github.com/CloAI/CommaAgents
